subunitreporter/__init__.py
subunitreporter/_metadata.py
subunitreporter/test/__init__.py
subunitreporter/test/cases.py
subunitreporter/test/test_distreporter_integration.py
twisted/plugins/subunitreporter.py
subunitreporter-23.8.0.dist-info/LICENSE
subunitreporter-23.8.0.dist-info/METADATA
subunitreporter-23.8.0.dist-info/WHEEL
subunitreporter-23.8.0.dist-info/top_level.txt
subunitreporter-23.8.0.dist-info/RECORD
