Metadata-Version: 2.1
Name: subunitreporter
Version: 23.8.0
Summary: A Twisted Trial reporter which emits Subunit v2 streams.
Home-page: https://github.com/LeastAuthority/subunitreporter
Author: subunitreporter Developers
License: MIT
License-File: LICENSE
Requires-Dist: zope.interface
Requires-Dist: attrs
Requires-Dist: testtools
Requires-Dist: python-subunit
Requires-Dist: twisted
